keras_declarative/__about__.py
keras_declarative/__init__.py
keras_declarative/cli.py
keras_declarative/config.py
keras_declarative/io.py
keras_declarative/objects.py
keras_declarative/predicates.py
keras_declarative/util.py
keras_declarative/workflows.py
keras_declarative/hyperparams/__init__.py
keras_declarative/hyperparams/base_config.py
keras_declarative/hyperparams/base_config_test.py
keras_declarative/hyperparams/oneof.py
keras_declarative/hyperparams/oneof_test.py
keras_declarative/hyperparams/params_dict.py
keras_declarative/hyperparams/params_dict_test.py
keras_declarative-0.6.0.dist-info/LICENSE
keras_declarative-0.6.0.dist-info/METADATA
keras_declarative-0.6.0.dist-info/WHEEL
keras_declarative-0.6.0.dist-info/entry_points.txt
keras_declarative-0.6.0.dist-info/top_level.txt
keras_declarative-0.6.0.dist-info/zip-safe
keras_declarative-0.6.0.dist-info/RECORD
