Metadata-Version: 2.1
Name: keras-declarative
Version: 0.6.0
Summary: A declarative Keras interface.
Home-page: https://github.com/mrphys/keras-declarative
Author: Javier Montalt Tordera
Author-email: javier.montalt@outlook.com
License: Apache 2.0
Keywords: tensorflow,keras,machine learning,ml
Platform: UNKNOWN
Classifier: Development Status :: 3 - Alpha
Classifier: Environment :: GPU
Classifier: Environment :: GPU :: NVIDIA CUDA
Classifier: Intended Audience :: Developers
Classifier: Intended Audience :: Science/Research
Classifier: License :: OSI Approved :: Apache Software License
Classifier: Operating System :: OS Independent
Classifier: Programming Language :: C++
Classifier: Programming Language :: Python :: 3
Classifier: Programming Language :: Python :: 3.7
Classifier: Programming Language :: Python :: 3.8
Classifier: Programming Language :: Python :: 3.9
Classifier: Topic :: Scientific/Engineering :: Mathematics
Classifier: Topic :: Software Development :: Libraries
Classifier: Topic :: Software Development :: Libraries :: Python Modules
Requires-Python: >=3.7
License-File: LICENSE
Requires-Dist: h5py
Requires-Dist: keras-tuner
Requires-Dist: pandas
Requires-Dist: pyyaml
Requires-Dist: tensorflow
Requires-Dist: tensorflow-datasets
Requires-Dist: tensorflow-io
